virvar/__init__.py
virvar/virvar.py
virvar-1.1.0.dist-info/METADATA
virvar-1.1.0.dist-info/WHEEL
virvar-1.1.0.dist-info/entry_points.txt
virvar-1.1.0.dist-info/licenses/LICENSE
virvar-1.1.0.dist-info/RECORD
