Metadata-Version: 2.4
Name: virvar
Version: 1.1.0
Summary: virvar is a Python utility designed to manage environment variables in virtual environments (venv)
Project-URL: Homepage, https://gitlab.com/lhndev1/virvar
Project-URL: Issues, https://gitlab.com/lhndev1/virvar/-/issues
Project-URL: Organization, https://lhndev.com
Author-email: vince06fr <vince06fr@gmail.com>, Liberty Hosting & Development <contact@lhndev.org>
License-File: LICENSE
Classifier: License :: OSI Approved :: MIT License
Classifier: Operating System :: OS Independent
Classifier: Programming Language :: Python :: 3
Requires-Python: >=3.9
